i3menu/__init__.py
i3menu/app.py
i3menu/cmds.py
i3menu/config.py
i3menu/connector.py
i3menu/exceptions.py
i3menu/i18n.py
i3menu/menu.py
i3menu/utils.py
i3menu/locale/it/LC_MESSAGES/i3-rofi.po
i3menu-3.0.data/scripts/i3menu
i3menu-3.0.dist-info/DESCRIPTION.rst
i3menu-3.0.dist-info/METADATA
i3menu-3.0.dist-info/RECORD
i3menu-3.0.dist-info/WHEEL
i3menu-3.0.dist-info/entry_points.txt
i3menu-3.0.dist-info/metadata.json
i3menu-3.0.dist-info/top_level.txt
