Metadata-Version: 2.0
Name: i3menu
Version: 3.0
Summary: a set of menus based on Rofi or dmenu to interact with i3wm
Home-page: https://github.com/giacomos/i3menu
Author: Giacomo Spettoli
Author-email: giacomo.spettoli@gmail.com
License: GPLv3
Keywords: i3 i3wm rofi dmenu
Platform: UNKNOWN
Classifier: Development Status :: 4 - Beta
Classifier: License :: OSI Approved :: GNU General Public License v3 or later (GPLv3+)
Classifier: Operating System :: Unix
Classifier: Topic :: Desktop Environment :: Window Managers
Classifier: Programming Language :: Python
Classifier: Programming Language :: Python :: 2.7
Classifier: Programming Language :: Python :: 3
Classifier: Programming Language :: Python :: 3.3
Classifier: Programming Language :: Python :: 3.4
Classifier: Programming Language :: Python :: 3.5
Requires-Dist: argparse
Requires-Dist: i3ipc
Requires-Dist: setuptools
